enumeration/__init__.py
enumeration/apps.py
enumeration/const.py
enumeration/formatter.py
enumeration/manager.py
enumeration/mixins.py
enumeration/models.py
enumeration/validators.py
enumeration/migrations/0001_initial.py
enumeration/migrations/0002_alter_counter_id_alter_gap_id_alter_sequence_id.py
enumeration/migrations/__init__.py
enumeration/tests/__init__.py
enumeration/tests/apps.py
enumeration/tests/models.py
enumeration/tests/settings.py
enumeration/tests/test_consume_gap.py
enumeration/tests/test_format.py
enumeration/tests/test_format_validator.py
enumeration/tests/test_get_next.py
enumeration/tests/test_get_number.py
enumeration/tests/test_increment.py
enumeration/tests/test_misc.py
enumeration/tests/test_model_mixin.py
enumeration/tests/migrations/0001_initial.py
enumeration/tests/migrations/__init__.py
django_enumeration-2.0.0.dist-info/METADATA
django_enumeration-2.0.0.dist-info/WHEEL
django_enumeration-2.0.0.dist-info/RECORD
