Metadata-Version: 2.3
Name: django-enumeration
Version: 2.0.0
Summary: Robust django enumeration sequences
Author-email: Mārtiņš Šulcs <shulcsm@gmail.com>
License: MIT
Classifier: Framework :: Django
Classifier: Intended Audience :: Developers
Classifier: Topic :: Software Development :: Libraries :: Python Modules
Requires-Python: >=3.8
Requires-Dist: django>=4
